dj_easy_xls/__init__.py
dj_easy_xls/main.py
dj_easy_xls-0.2.3.dist-info/LICENSE
dj_easy_xls-0.2.3.dist-info/METADATA
dj_easy_xls-0.2.3.dist-info/WHEEL
dj_easy_xls-0.2.3.dist-info/top_level.txt
dj_easy_xls-0.2.3.dist-info/RECORD
